conductor/ExchangeConductor.py
conductor/__init__.py
conductor/extractor/DataExtractor.py
conductor/extractor/__init__.py
conductor/instrument/InstrumentExchangeHandler.py
conductor/instrument/__init__.py
conductor/provider/ExchangeDataProvider.py
conductor/provider/__init__.py
conductor/transform/ExchangeTransformer.py
conductor/transform/__init__.py
persuader_technology_automata_exchange_conductor-0.1.6.dist-info/LICENSE
persuader_technology_automata_exchange_conductor-0.1.6.dist-info/METADATA
persuader_technology_automata_exchange_conductor-0.1.6.dist-info/WHEEL
persuader_technology_automata_exchange_conductor-0.1.6.dist-info/top_level.txt
persuader_technology_automata_exchange_conductor-0.1.6.dist-info/RECORD
