Metadata-Version: 2.1
Name: persuader-technology-automata-exchange-conductor
Version: 0.1.6
Summary: Automata Exchange Conductor
Author: Persuader Technology
Author-email: software@persuader.technology
License: UNLICENSE
Classifier: Programming Language :: Python :: 3
License-File: LICENSE
Requires-Dist: persuader-technology-automata-core (>=0.6.0)
Requires-Dist: persuader-technology-automata-logger (>=0.0.5)
Requires-Dist: persuader-technology-automata-exchange-transform-repository (>=0.2.0)
Requires-Dist: persuader-technology-automata-exchange-repository (>=0.3.0)
Requires-Dist: persuader-technology-automata-config (>=0.1.6)
